{"action":{"identity":{"address":"N\u0000sourcecred\u0000core\u0000IDENTITY\u00005zHMgDegemneRsxywlybvA\u0000","aliases":[],"id":"5zHMgDegemneRsxywlybvA","name":"waynevest","subtype":"USER"},"type":"CREATE_IDENTITY"},"ledgerTimestamp":1630874345005,"uuid":"oxu5wtWZeymb3OjeYpmDeA","version":"1"}
{"action":{"alias":{"address":"N\u0000sourcecred\u0000discourse\u0000user\u0000https://forum.weinvest.money\u0000waynevest\u0000","description":"discourse/[@waynevest](https://forum.weinvest.money/u/waynevest/)"},"identityId":"5zHMgDegemneRsxywlybvA","type":"ADD_ALIAS"},"ledgerTimestamp":1630874345005,"uuid":"YuL1IkwdAQxAwEztllafZg","version":"1"}
{"action":{"identity":{"address":"N\u0000sourcecred\u0000core\u0000IDENTITY\u0000b9jI7Dom1RnWVyenx2do4w\u0000","aliases":[],"id":"b9jI7Dom1RnWVyenx2do4w","name":"system","subtype":"BOT"},"type":"CREATE_IDENTITY"},"ledgerTimestamp":1630874345006,"uuid":"0NFMxFMoXvmhEyjpIdfjLw","version":"1"}
{"action":{"alias":{"address":"N\u0000sourcecred\u0000discourse\u0000user\u0000https://forum.weinvest.money\u0000system\u0000","description":"discourse/[@system](https://forum.weinvest.money/u/system/)"},"identityId":"b9jI7Dom1RnWVyenx2do4w","type":"ADD_ALIAS"},"ledgerTimestamp":1630874345006,"uuid":"TpQRHZTXl7iLBOQi68aJ0A","version":"1"}
{"action":{"identity":{"address":"N\u0000sourcecred\u0000core\u0000IDENTITY\u0000kT5aO4zeGBTqrBl8IYVmSw\u0000","aliases":[],"id":"kT5aO4zeGBTqrBl8IYVmSw","name":"xavier","subtype":"USER"},"type":"CREATE_IDENTITY"},"ledgerTimestamp":1630880616946,"uuid":"D9eoAZkAhoKUWQ5ZaogM4w","version":"1"}
{"action":{"identityId":"kT5aO4zeGBTqrBl8IYVmSw","type":"TOGGLE_ACTIVATION"},"ledgerTimestamp":1630880625013,"uuid":"Lf1U4Gep5CQaJlgrROkmzg","version":"1"}
{"action":{"identityId":"5zHMgDegemneRsxywlybvA","type":"TOGGLE_ACTIVATION"},"ledgerTimestamp":1630895315599,"uuid":"cDejNWIeHGevpquATg2WyQ","version":"1"}
{"action":{"identity":{"address":"N\u0000sourcecred\u0000core\u0000IDENTITY\u0000ouRz1T6kBQJ2L1kpYyxIZg\u0000","aliases":[],"id":"ouRz1T6kBQJ2L1kpYyxIZg","name":"SourceCred","subtype":"PROJECT"},"type":"CREATE_IDENTITY"},"ledgerTimestamp":1630932882035,"uuid":"gS7MGnUzKGSBRv6EJwErag","version":"1"}
{"action":{"identityId":"ouRz1T6kBQJ2L1kpYyxIZg","type":"TOGGLE_ACTIVATION"},"ledgerTimestamp":1630932882036,"uuid":"Ec3BWlBPPEyMWU2l3kxRsg","version":"1"}
{"action":{"identity":{"address":"N\u0000sourcecred\u0000core\u0000IDENTITY\u0000OvBed3QneQCjG9PQ03aA1Q\u0000","aliases":[],"id":"OvBed3QneQCjG9PQ03aA1Q","name":"rochellew","subtype":"USER"},"type":"CREATE_IDENTITY"},"ledgerTimestamp":1635900428869,"uuid":"GGJzlmnl8Oaax1FjM1g73g","version":"1"}
{"action":{"alias":{"address":"N\u0000sourcecred\u0000discourse\u0000user\u0000https://forum.weinvest.money\u0000rochellew\u0000","description":"discourse/[@rochellew](https://forum.weinvest.money/u/rochellew/)"},"identityId":"OvBed3QneQCjG9PQ03aA1Q","type":"ADD_ALIAS"},"ledgerTimestamp":1635900428869,"uuid":"wES95CR2GAVtly22BbNMfA","version":"1"}
{"action":{"identity":{"address":"N\u0000sourcecred\u0000core\u0000IDENTITY\u0000kBu0F4gvu6XlAaey6VgxqA\u0000","aliases":[],"id":"kBu0F4gvu6XlAaey6VgxqA","name":"williamreyes","subtype":"USER"},"type":"CREATE_IDENTITY"},"ledgerTimestamp":1635900428870,"uuid":"EDpZLRxOwJkpG2zGAWZ68w","version":"1"}
{"action":{"alias":{"address":"N\u0000sourcecred\u0000discourse\u0000user\u0000https://forum.weinvest.money\u0000williamreyes\u0000","description":"discourse/[@williamreyes](https://forum.weinvest.money/u/williamreyes/)"},"identityId":"kBu0F4gvu6XlAaey6VgxqA","type":"ADD_ALIAS"},"ledgerTimestamp":1635900428871,"uuid":"aRexPX60IKrkm90gxPQztg","version":"1"}
{"action":{"identity":{"address":"N\u0000sourcecred\u0000core\u0000IDENTITY\u000076BLCoNIEmS7JYuKs24mnA\u0000","aliases":[],"id":"76BLCoNIEmS7JYuKs24mnA","name":"ilealmon","subtype":"USER"},"type":"CREATE_IDENTITY"},"ledgerTimestamp":1635900428872,"uuid":"YuvK4SrOFJxwAdQr1VVmrw","version":"1"}
{"action":{"alias":{"address":"N\u0000sourcecred\u0000discourse\u0000user\u0000https://forum.weinvest.money\u0000ilealmon\u0000","description":"discourse/[@ilealmon](https://forum.weinvest.money/u/ilealmon/)"},"identityId":"76BLCoNIEmS7JYuKs24mnA","type":"ADD_ALIAS"},"ledgerTimestamp":1635900428872,"uuid":"ulLwm6RMiQ5mooX2fKav3Q","version":"1"}
{"action":{"identity":{"address":"N\u0000sourcecred\u0000core\u0000IDENTITY\u0000WVZakB70q9oeonUrFlexmQ\u0000","aliases":[],"id":"WVZakB70q9oeonUrFlexmQ","name":"mantedan","subtype":"USER"},"type":"CREATE_IDENTITY"},"ledgerTimestamp":1635900428873,"uuid":"mh80D5m0PEgJIE9LoyMZTQ","version":"1"}
{"action":{"alias":{"address":"N\u0000sourcecred\u0000discourse\u0000user\u0000https://forum.weinvest.money\u0000mantedan\u0000","description":"discourse/[@mantedan](https://forum.weinvest.money/u/mantedan/)"},"identityId":"WVZakB70q9oeonUrFlexmQ","type":"ADD_ALIAS"},"ledgerTimestamp":1635900428873,"uuid":"fEzgvr29yA76ZqKq8FdROg","version":"1"}
{"action":{"identity":{"address":"N\u0000sourcecred\u0000core\u0000IDENTITY\u0000lQEdG9Q4BntzvoZbR8dinQ\u0000","aliases":[],"id":"lQEdG9Q4BntzvoZbR8dinQ","name":"hundialp","subtype":"USER"},"type":"CREATE_IDENTITY"},"ledgerTimestamp":1635900428874,"uuid":"DrRl5J3aaF59wNY2bM3vpg","version":"1"}
{"action":{"alias":{"address":"N\u0000sourcecred\u0000discourse\u0000user\u0000https://forum.weinvest.money\u0000hundialp\u0000","description":"discourse/[@hundialp](https://forum.weinvest.money/u/hundialp/)"},"identityId":"lQEdG9Q4BntzvoZbR8dinQ","type":"ADD_ALIAS"},"ledgerTimestamp":1635900428874,"uuid":"CpS021kjXT5d2U99E17Swg","version":"1"}
{"action":{"identity":{"address":"N\u0000sourcecred\u0000core\u0000IDENTITY\u0000FlaZef3EdkksAB3QB7DCnQ\u0000","aliases":[],"id":"FlaZef3EdkksAB3QB7DCnQ","name":"ikulyatin","subtype":"USER"},"type":"CREATE_IDENTITY"},"ledgerTimestamp":1635900428875,"uuid":"GREpy0lyqDyLQ4dlOc5JgA","version":"1"}
{"action":{"alias":{"address":"N\u0000sourcecred\u0000discourse\u0000user\u0000https://forum.weinvest.money\u0000ikulyatin\u0000","description":"discourse/[@ikulyatin](https://forum.weinvest.money/u/ikulyatin/)"},"identityId":"FlaZef3EdkksAB3QB7DCnQ","type":"ADD_ALIAS"},"ledgerTimestamp":1635900428875,"uuid":"TE76zd4PulrL7mzbnUBGlw","version":"1"}
{"action":{"identity":{"address":"N\u0000sourcecred\u0000core\u0000IDENTITY\u0000u76jG9OBlKgeQetXkORYRA\u0000","aliases":[],"id":"u76jG9OBlKgeQetXkORYRA","name":"peastime","subtype":"USER"},"type":"CREATE_IDENTITY"},"ledgerTimestamp":1635900428875,"uuid":"sGLzYqHbBs6jJy65ekQB8g","version":"1"}
{"action":{"alias":{"address":"N\u0000sourcecred\u0000discourse\u0000user\u0000https://forum.weinvest.money\u0000peastime\u0000","description":"discourse/[@peastime](https://forum.weinvest.money/u/peastime/)"},"identityId":"u76jG9OBlKgeQetXkORYRA","type":"ADD_ALIAS"},"ledgerTimestamp":1635900428875,"uuid":"EdQ5t9pAE7EPl7AILpINUA","version":"1"}
{"action":{"identity":{"address":"N\u0000sourcecred\u0000core\u0000IDENTITY\u0000K4kVVM27oRQUxNw17DBGpg\u0000","aliases":[],"id":"K4kVVM27oRQUxNw17DBGpg","name":"dighnium","subtype":"USER"},"type":"CREATE_IDENTITY"},"ledgerTimestamp":1635900428876,"uuid":"jOlPhbaRSwsAzxKm0TbKeQ","version":"1"}
{"action":{"alias":{"address":"N\u0000sourcecred\u0000discourse\u0000user\u0000https://forum.weinvest.money\u0000dighnium\u0000","description":"discourse/[@dighnium](https://forum.weinvest.money/u/dighnium/)"},"identityId":"K4kVVM27oRQUxNw17DBGpg","type":"ADD_ALIAS"},"ledgerTimestamp":1635900428876,"uuid":"pP8S5syzRNrkfmZM53pE8A","version":"1"}
